{\n  \"ranks\": [\n    {\n      \"name\": \"Admin\",\n      \"permissions\": [\"manage_roles\", \"manage_server\", \"manage_messages\"]\n    },\n    {\n      \"name\": \"Moderator\",\n      \"permissions\": [\"manage_messages\", \"kick_members\"]\n    },\n    {\n      \"name\": \"Staff\",\n      \"permissions\": []\n    }\n  ],\n  \"strikes\": {\n    \"max_strikes\": 3,\n    \"strike_duration\": \"30d\"\n  },\n  \"special_roles\": [\n    {\n      \"name\": \"Bots\",\n      \"permissions\": [\"use_commands\"]\n    },\n    {\n      \"name\": \"Developers\",\n      \"permissions\": [\"manage_roles\", \"manage_messages\"]\n    }\n  ]\n}